[{"year":"2023","month":"10","day":"1","calories_elementary":null,"calories_junior_high":null,"menu_items":[]},{"year":"2023","month":"10","day":"2","calories_elementary":"618","calories_junior_high":"772","menu_items":["ごはん","さば銀紙焼き","きゅうりとたくあんの和え物","大根と豚肉の煮物","牛乳"]},{"year":"2023","month":"10","day":"3","calories_elementary":"655","calories_junior_high":"815","menu_items":["ごはん","けんちん信田の甘みそかけ","もやしの酢の物","鶏肉と白菜のすまし汁","牛乳"]},{"year":"2023","month":"10","day":"4","calories_elementary":"649","calories_junior_high":"771","menu_items":["きなこ揚げパン","ツナサラダ","ノンエッグマヨネーズ","ミートボールのトマト煮","ヨーグルト","牛乳"]},{"year":"2023","month":"10","day":"5","calories_elementary":"590","calories_junior_high":"738","menu_items":["ごはん","春巻き","バンサンスー","わかめスープ","牛乳"]},{"year":"2023","month":"10","day":"6","calories_elementary":"647","calories_junior_high":"810","menu_items":["ごはん","栗ご飯の具","いわしの梅煮","豚汁","牛乳"]},{"year":"2023","month":"10","day":"7","calories_elementary":null,"calories_junior_high":null,"menu_items":[]},{"year":"2023","month":"10","day":"8","calories_elementary":null,"calories_junior_high":null,"menu_items":[]},{"year":"2023","month":"10","day":"9","calories_elementary":null,"calories_junior_high":null,"menu_items":[]},{"year":"2023","month":"10","day":"10","calories_elementary":"605","calories_junior_high":"747","menu_items":["中華めん","五目中華スープ","えびしゅうまい","切干し大根のナムル","ブルーベリーゼリー","牛乳"]},{"year":"2023","month":"10","day":"11","calories_elementary":"649","calories_junior_high":"808","menu_items":["ごはん","厚焼き卵","小松菜とかつおの和え物","生揚げの旨煮","牛乳"]},{"year":"2023","month":"10","day":"12","calories_elementary":"659","calories_junior_high":"818","menu_items":["ごはん","ハヤシライス","ハムステーキ","豆豆サラダ","乾燥小魚","牛乳"]},{"year":"2023","month":"10","day":"13","calories_elementary":"603","calories_junior_high":"778","menu_items":["ごはん","大学芋","いんげんのごま和え","実だくさん汁","牛乳"]},{"year":"2023","month":"10","day":"14","calories_elementary":null,"calories_junior_high":null,"menu_items":[]},{"year":"2023","month":"10","day":"15","calories_elementary":null,"calories_junior_high":null,"menu_items":[]},{"year":"2023","month":"10","day":"16","calories_elementary":"665","calories_junior_high":"830","menu_items":["麦ごはん","ホキの甘酢ダレかけ","野菜のナムル","マーボー豆腐","牛乳"]},{"year":"2023","month":"10","day":"17","calories_elementary":"588","calories_junior_high":"733","menu_items":["サンドイッチロールパン","オムレツケチャップソース","キャベツとアスパラのソテー","豆乳スープ","キャンディチーズ","牛乳"]},{"year":"2023","month":"10","day":"18","calories_elementary":"618","calories_junior_high":"806","menu_items":["ごはん","子持ちししゃもフライ","ブロッコリーの和え物","ちゃんこ汁","牛乳"]},{"year":"2023","month":"10","day":"19","calories_elementary":"596","calories_junior_high":"745","menu_items":["ごはん","大葉入りハンバーグおろしだれ","いかと里芋の煮物","すまし汁","牛乳"]},{"year":"2023","month":"10","day":"20","calories_elementary":"571","calories_junior_high":"707","menu_items":["ごはん","肉じゃが","白菜のゆかり和え","みかん","牛乳"]},{"year":"2023","month":"10","day":"21","calories_elementary":null,"calories_junior_high":null,"menu_items":[]},{"year":"2023","month":"10","day":"22","calories_elementary":null,"calories_junior_high":null,"menu_items":[]},{"year":"2023","month":"10","day":"23","calories_elementary":"651","calories_junior_high":"814","menu_items":["麦ごはん","カレー","フランクフルト","だいコーンサラダ","牛乳"]},{"year":"2023","month":"10","day":"24","calories_elementary":"645","calories_junior_high":"822","menu_items":["ソフトめん","和風汁","レバー入りつくね","元気サラダ","牛乳"]},{"year":"2023","month":"10","day":"25","calories_elementary":"644","calories_junior_high":"811","menu_items":["ごはん","さんまのかば焼き","野菜の梅肉和え","沢煮椀","牛乳"]},{"year":"2023","month":"10","day":"26","calories_elementary":"578","calories_junior_high":"721","menu_items":["ごはん","豚肉と生揚げのみそ煮","いかときゅうりの酢の物","りんご","牛乳"]},{"year":"2023","month":"10","day":"27","calories_elementary":"643","calories_junior_high":"794","menu_items":["ごはん","コロッケ","ひじきの炒め煮","きのこ汁","牛乳"]},{"year":"2023","month":"10","day":"28","calories_elementary":null,"calories_junior_high":null,"menu_items":[]},{"year":"2023","month":"10","day":"29","calories_elementary":null,"calories_junior_high":null,"menu_items":[]},{"year":"2023","month":"10","day":"30","calories_elementary":"575","calories_junior_high":"744","menu_items":["ごはん","ぎょうざ","エリンギの野菜炒め","中華スープ","牛乳"]},{"year":"2023","month":"10","day":"31","calories_elementary":"689","calories_junior_high":"848","menu_items":["ロールパン","鶏の照り焼き","コールスローサラダ","かぼちゃスープ","ココア牛乳の素","牛乳"]}]