[{"year":"2022","month":"10","day":"3","main_dish":"ごはん","menu_item_1":"にじますの甘露煮","menu_item_2":"梅肉和え","menu_item_3":"さつま芋のみそ汁","menu_item_4":null,"menu_item_5":null,"menu_item_6":null,"drink":"牛乳","calories_elementary":"601","calories_junior_high":"773"},{"year":"2022","month":"10","day":"4","main_dish":"りんごパン","menu_item_1":"いかフライのレモンソース","menu_item_2":"ブロッコリーサラダ","menu_item_3":"豆乳のコーンスープ","menu_item_4":null,"menu_item_5":null,"menu_item_6":null,"drink":"牛乳","calories_elementary":"674","calories_junior_high":"837"},{"year":"2022","month":"10","day":"5","main_dish":"麦ごはん","menu_item_1":"しゅうまい","menu_item_2":"バンサンスー","menu_item_3":"マーボー豆腐","menu_item_4":null,"menu_item_5":null,"menu_item_6":null,"drink":"牛乳","calories_elementary":"654","calories_junior_high":"841"},{"year":"2022","month":"10","day":"6","main_dish":"ごはん","menu_item_1":"さんまのみぞれ煮","menu_item_2":"大豆のおかか煮","menu_item_3":"沢煮椀","menu_item_4":null,"menu_item_5":null,"menu_item_6":null,"drink":"牛乳","calories_elementary":"608","calories_junior_high":"764"},{"year":"2022","month":"10","day":"7","main_dish":"ソフトめん","menu_item_1":"秋なすのミートソース","menu_item_2":"フランクフルト","menu_item_3":"にんじんサラダ","menu_item_4":"ブルーベリーゼリー","menu_item_5":null,"menu_item_6":null,"drink":"牛乳","calories_elementary":"761","calories_junior_high":"945"},{"year":"2022","month":"10","day":"11","main_dish":"ごはん","menu_item_1":"鶏肉のから揚げ","menu_item_2":"たくあん和え","menu_item_3":"里芋のみそ汁","menu_item_4":null,"menu_item_5":null,"menu_item_6":null,"drink":"牛乳","calories_elementary":"644","calories_junior_high":"804"},{"year":"2022","month":"10","day":"12","main_dish":"麦ごはん","menu_item_1":"厚焼き卵","menu_item_2":"金平ごぼう","menu_item_3":"すまし汁","menu_item_4":"ぶどうヨーグルト","menu_item_5":null,"menu_item_6":null,"drink":"牛乳","calories_elementary":"637","calories_junior_high":"781"},{"year":"2022","month":"10","day":"13","main_dish":"きなこ揚げパン","menu_item_1":"米粉のマカロニサラダ","menu_item_2":"ミートボールシチュー","menu_item_3":"キャンディチーズ","menu_item_4":null,"menu_item_5":null,"menu_item_6":null,"drink":"牛乳","calories_elementary":"620","calories_junior_high":"753"},{"year":"2022","month":"10","day":"14","main_dish":"ごはん","menu_item_1":"鮭の塩焼き","menu_item_2":"大学芋","menu_item_3":"ちゃんこ汁","menu_item_4":null,"menu_item_5":null,"menu_item_6":null,"drink":"牛乳","calories_elementary":"628","calories_junior_high":"814"},{"year":"2022","month":"10","day":"17","main_dish":"ごはん","menu_item_1":"きのこカレー","menu_item_2":"ハムステーキ","menu_item_3":"コールスローサラダ","menu_item_4":"アーモンド入り小魚","menu_item_5":null,"menu_item_6":null,"drink":"牛乳","calories_elementary":"672","calories_junior_high":"842"},{"year":"2022","month":"10","day":"18","main_dish":"麦ごはん","menu_item_1":"揚げぎょうざ","menu_item_2":"ひじきの中華和え","menu_item_3":"中華スープ","menu_item_4":null,"menu_item_5":null,"menu_item_6":null,"drink":"牛乳","calories_elementary":"607","calories_junior_high":"793"},{"year":"2022","month":"10","day":"19","main_dish":"ごはん","menu_item_1":"うなぎ散らしの具（うなぎ）","menu_item_2":"うなぎ散らしの具（野菜）","menu_item_3":"半田の卵かき玉汁","menu_item_4":"水ようかん","menu_item_5":null,"menu_item_6":null,"drink":"牛乳","calories_elementary":"609","calories_junior_high":"763"},{"year":"2022","month":"10","day":"20","main_dish":"ごはん","menu_item_1":"いわしのしょうが煮","menu_item_2":"切干し大根の甘酢和え","menu_item_3":"肉じゃが","menu_item_4":null,"menu_item_5":null,"menu_item_6":null,"drink":"牛乳","calories_elementary":"666","calories_junior_high":"835"},{"year":"2022","month":"10","day":"21","main_dish":"うどん","menu_item_1":"肉うどん（汁）","menu_item_2":"けんちん信田の香味だれ","menu_item_3":"栗の豆乳抹茶ゼリー和え","menu_item_4":null,"menu_item_5":null,"menu_item_6":null,"drink":"牛乳","calories_elementary":"742","calories_junior_high":"872"},{"year":"2022","month":"10","day":"24","main_dish":"麦ごはん","menu_item_1":"ビビンバ（肉）","menu_item_2":"ビビンバ（ナムル）","menu_item_3":"トック入りわかめスープ","menu_item_4":"ヨーグルト","menu_item_5":null,"menu_item_6":null,"drink":"牛乳","calories_elementary":"697","calories_junior_high":"871"},{"year":"2022","month":"10","day":"25","main_dish":"愛知の米粉入りパン","menu_item_1":"オムレツの豆乳ホワイトソースかけ","menu_item_2":"さつま芋サラダ","menu_item_3":"ノンエッグマヨネーズ","menu_item_4":"コンソメスープ","menu_item_5":null,"menu_item_6":null,"drink":"牛乳","calories_elementary":"649","calories_junior_high":"737"},{"year":"2022","month":"10","day":"26","main_dish":"ごはん","menu_item_1":"鶏肉の照り焼き","menu_item_2":"キャベツのレモン醤油和え","menu_item_3":"えび団子汁","menu_item_4":"味付乾燥豆腐","menu_item_5":null,"menu_item_6":null,"drink":"牛乳","calories_elementary":"621","calories_junior_high":"769"},{"year":"2022","month":"10","day":"27","main_dish":"ごはん","menu_item_1":"小松菜とかつおの和え物","menu_item_2":"煮みそ","menu_item_3":"りんご","menu_item_4":null,"menu_item_5":null,"menu_item_6":null,"drink":"牛乳","calories_elementary":"600","calories_junior_high":"744"},{"year":"2022","month":"10","day":"28","main_dish":"ごはん","menu_item_1":"さんまのみぞれ煮","menu_item_2":"ひじきの炒め煮","menu_item_3":"のっぺい汁","menu_item_4":null,"menu_item_5":null,"menu_item_6":null,"drink":"牛乳","calories_elementary":"586","calories_junior_high":"752"},{"year":"2022","month":"10","day":"31","main_dish":"クロスロールパン","menu_item_1":"かぼちゃ入りハンバーグのバーベキューソースかけ","menu_item_2":"ブロッコリーのカレー炒め","menu_item_3":"ミネストローネ","menu_item_4":"パンプキンババロア","menu_item_5":null,"menu_item_6":null,"drink":"牛乳","calories_elementary":"670","calories_junior_high":"853"}]