[
  {
    "year": "2017",
    "month": "2",
    "day": "1",
    "calories_elementary": "660",
    "calories_junior_high": "828",
    "menu_items": [
      "ごはん",
      "さんまのぎんがみやき",
      "なのはなあえ",
      "にくじゃが"
    ]
  },
  {
    "year": "2017",
    "month": "2",
    "day": "2",
    "calories_elementary": "612",
    "calories_junior_high": "765",
    "menu_items": ["ごはん", "コロッケ", "かんとうに", "キャベツのゆかりあえ"]
  },
  {
    "year": "2017",
    "month": "2",
    "day": "3",
    "calories_elementary": "765",
    "calories_junior_high": "943",
    "menu_items": [
      "ごはん",
      "いわしフライ",
      "せつぶんまめ",
      "ちゃんこなべ",
      "こまつなとツナのあえもの"
    ]
  },
  {
    "year": "2017",
    "month": "2",
    "day": "4",
    "calories_elementary": null,
    "calories_junior_high": null,
    "menu_items": []
  },
  {
    "year": "2017",
    "month": "2",
    "day": "5",
    "calories_elementary": null,
    "calories_junior_high": null,
    "menu_items": []
  },
  {
    "year": "2017",
    "month": "2",
    "day": "6",
    "calories_elementary": "624",
    "calories_junior_high": "742",
    "menu_items": [
      "きなこあげパン",
      "ビーンズスープ",
      "ごぼうサラダマヨネーズ",
      "かたぬきチーズ"
    ]
  },
  {
    "year": "2017",
    "month": "2",
    "day": "7",
    "calories_elementary": "698",
    "calories_junior_high": "854",
    "menu_items": [
      "ごはん",
      "ぶりのてりやき",
      "きりぼしだいこんのにもの",
      "かきたまじる",
      "こうはくもち"
    ]
  },
  {
    "year": "2017",
    "month": "2",
    "day": "8",
    "calories_elementary": "584",
    "calories_junior_high": "724",
    "menu_items": [
      "ごはん",
      "ビビンバ（にく）",
      "ビビンバ（ナムル）",
      "ちゅうかスープ",
      "ヨーグルト"
    ]
  },
  {
    "year": "2017",
    "month": "2",
    "day": "9",
    "calories_elementary": "654",
    "calories_junior_high": "803",
    "menu_items": [
      "むぎごはん",
      "ツナそぼろ",
      "あつやきたまご（のり）",
      "やさいのうまに"
    ]
  },
  {
    "year": "2017",
    "month": "2",
    "day": "10",
    "calories_elementary": "633",
    "calories_junior_high": "798",
    "menu_items": [
      "ちゅうかめん",
      "ごもくちゅうかスープ",
      "にくまん",
      "もやしのあえもの"
    ]
  },
  {
    "year": "2017",
    "month": "2",
    "day": "11",
    "calories_elementary": null,
    "calories_junior_high": null,
    "menu_items": []
  },
  {
    "year": "2017",
    "month": "2",
    "day": "12",
    "calories_elementary": null,
    "calories_junior_high": null,
    "menu_items": []
  },
  {
    "year": "2017",
    "month": "2",
    "day": "13",
    "calories_elementary": "612",
    "calories_junior_high": "772",
    "menu_items": [
      "ごはん",
      "さけのしおやき",
      "だいこんとぶたにくのにもの",
      "だいずのごもくいそに"
    ]
  },
  {
    "year": "2017",
    "month": "2",
    "day": "14",
    "calories_elementary": "683",
    "calories_junior_high": "823",
    "menu_items": [
      "むぎごはん",
      "ハヤシライス",
      "だいコーンサラダドレッシング",
      "チョコだんご"
    ]
  },
  {
    "year": "2017",
    "month": "2",
    "day": "15",
    "calories_elementary": "609",
    "calories_junior_high": "784",
    "menu_items": [
      "ごはん",
      "にくしゅうまい(２こ・３こ)",
      "なまあげのちゅうかに",
      "ビーフンいため"
    ]
  },
  {
    "year": "2017",
    "month": "2",
    "day": "16",
    "calories_elementary": "716",
    "calories_junior_high": "891",
    "menu_items": [
      "レーズンロールパン",
      "ハンバーグのデミソース",
      "コーンクリームスープ",
      "えだまめサラダドレッシング"
    ]
  },
  {
    "year": "2017",
    "month": "2",
    "day": "17",
    "calories_elementary": "598",
    "calories_junior_high": "753",
    "menu_items": [
      "あかまいごはん",
      "みそおでん",
      "とりにくとれんこんのにもの",
      "かぶのこんぶあえ"
    ]
  },
  {
    "year": "2017",
    "month": "2",
    "day": "18",
    "calories_elementary": null,
    "calories_junior_high": null,
    "menu_items": []
  },
  {
    "year": "2017",
    "month": "2",
    "day": "19",
    "calories_elementary": null,
    "calories_junior_high": null,
    "menu_items": []
  },
  {
    "year": "2017",
    "month": "2",
    "day": "20",
    "calories_elementary": "613",
    "calories_junior_high": "786",
    "menu_items": [
      "はつがげんまいごはん",
      "とりにくとさつまいものかんこくふう",
      "はっぽうさい",
      "いよかん",
      "かんそうこざかな"
    ]
  },
  {
    "year": "2017",
    "month": "2",
    "day": "21",
    "calories_elementary": "675",
    "calories_junior_high": "841",
    "menu_items": ["ごはん", "ハムフライ", "はくさいのおかかあえ", "おやこに"]
  },
  {
    "year": "2017",
    "month": "2",
    "day": "22",
    "calories_elementary": "651",
    "calories_junior_high": "816",
    "menu_items": [
      "ごはん",
      "さばのぎんがみやき",
      "きんときまめのあまに",
      "さわにわん"
    ]
  },
  {
    "year": "2017",
    "month": "2",
    "day": "23",
    "calories_elementary": "553",
    "calories_junior_high": "704",
    "menu_items": [
      "わかめごはん",
      "うずらたまごくしフライ",
      "バンバンジーサラダ",
      "キムチスープ"
    ]
  },
  {
    "year": "2017",
    "month": "2",
    "day": "24",
    "calories_elementary": "627",
    "calories_junior_high": "737",
    "menu_items": [
      "うどん",
      "カレーなんばん",
      "やさいのしらすあえ",
      "フルーツポンチ"
    ]
  },
  {
    "year": "2017",
    "month": "2",
    "day": "25",
    "calories_elementary": null,
    "calories_junior_high": null,
    "menu_items": []
  },
  {
    "year": "2017",
    "month": "2",
    "day": "26",
    "calories_elementary": null,
    "calories_junior_high": null,
    "menu_items": []
  },
  {
    "year": "2017",
    "month": "2",
    "day": "27",
    "calories_elementary": "651",
    "calories_junior_high": "799",
    "menu_items": [
      "ごはん",
      "ししゃもフライのこうみソース(２ひき)",
      "ごもくきんぴら",
      "かすじる"
    ]
  },
  {
    "year": "2017",
    "month": "2",
    "day": "28",
    "calories_elementary": "602",
    "calories_junior_high": "761",
    "menu_items": [
      "ごはん",
      "にくだんごのすぶたふう",
      "やさいのナムル",
      "ワンタンスープ"
    ]
  }
]
